jutil/__init__.py
jutil/class_.py
jutil/exception.py
jutil/function.py
jutil/value.py
py_jutil-0.0.3.dist-info/METADATA
py_jutil-0.0.3.dist-info/WHEEL
py_jutil-0.0.3.dist-info/top_level.txt
py_jutil-0.0.3.dist-info/RECORD
