Metadata-Version: 2.1
Name: py-jutil
Version: 0.0.3
Summary: JUtil is a collection of useful functions, values, and classes for Python.
Author: Noah Wilhoite
Author-email: notnoah349@gmail.com
